AIFallbackLocator.py
DomRetryLibrary.py
domretrylibrary/__init__.py
domretrylibrary/ai_processor.py
domretrylibrary/core.py
domretrylibrary/keyword_handler.py
domretrylibrary/locator_manager.py
robot_aifallbacklocator-1.0.4.dist-info/licenses/LICENSE
robot_aifallbacklocator-1.0.4.dist-info/METADATA
robot_aifallbacklocator-1.0.4.dist-info/WHEEL
robot_aifallbacklocator-1.0.4.dist-info/top_level.txt
robot_aifallbacklocator-1.0.4.dist-info/RECORD
